[
  {
    "human_readable_name": "Uniswap Total Claimed Amount",
    "name": "uniswap_total_claims_amount",
    "metric": "uniswap_amount_claimed",
    "version": "2019-12-22",
    "access": "free",
    "selectors": ["slug"],
    "min_plan": {
      "SANAPI": "pro",
      "SANBASE": "free"
    },
    "aggregation": "last",
    "min_interval": "5m",
    "table": "intraday_metrics",
    "has_incomplete_data": false,
    "data_type": "timeseries",
    "docs_links": ["https://academy.santiment.net/metrics/deprecated-metrics/uniswap-airdrop-metrics"]
  },
  {
    "human_readable_name": "Uniswap Total Claims Count",
    "name": "uniswap_total_claims_count",
    "metric": "uniswap_claims",
    "version": "2019-12-22",
    "access": "free",
    "selectors": ["slug"],
    "min_plan": {
      "SANAPI": "pro",
      "SANBASE": "free"
    },
    "aggregation": "last",
    "min_interval": "5m",
    "table": "intraday_metrics",
    "has_incomplete_data": false,
    "data_type": "timeseries",
    "docs_links": ["https://academy.santiment.net/metrics/deprecated-metrics/uniswap-airdrop-metrics"]
  },
  {
    "human_readable_name": "Uniswap Total Claimed Amount for Users",
    "name": "uniswap_total_user_claims_amount",
    "metric": "uniswap_amount_user_claimed",
    "version": "2019-12-22",
    "access": "free",
    "selectors": ["slug"],
    "min_plan": {
      "SANAPI": "pro",
      "SANBASE": "free"
    },
    "aggregation": "last",
    "min_interval": "5m",
    "table": "intraday_metrics",
    "has_incomplete_data": false,
    "data_type": "timeseries",
    "docs_links": ["https://academy.santiment.net/metrics/deprecated-metrics/uniswap-airdrop-metrics"]
  },
  {
    "human_readable_name": "Uniswap Total Claims Count for Users",
    "name": "uniswap_total_user_claims_count",
    "metric": "uniswap_user_claims",
    "version": "2019-12-22",
    "access": "free",
    "selectors": ["slug"],
    "min_plan": {
      "SANAPI": "pro",
      "SANBASE": "free"
    },
    "aggregation": "last",
    "min_interval": "5m",
    "table": "intraday_metrics",
    "has_incomplete_data": false,
    "data_type": "timeseries",
    "docs_links": ["https://academy.santiment.net/metrics/deprecated-metrics/uniswap-airdrop-metrics"]
  },
  {
    "human_readable_name": "Uniswap Total Claimed Amount for Liquidity Providers",
    "name": "uniswap_total_lp_claims_amount",
    "metric": "uniswap_amount_lp_claimed",
    "version": "2019-12-22",
    "access": "free",
    "selectors": ["slug"],
    "min_plan": {
      "SANAPI": "pro",
      "SANBASE": "free"
    },
    "aggregation": "last",
    "min_interval": "5m",
    "table": "intraday_metrics",
    "has_incomplete_data": false,
    "data_type": "timeseries",
    "docs_links": ["https://academy.santiment.net/metrics/deprecated-metrics/uniswap-airdrop-metrics"]
  },
  {
    "human_readable_name": "Uniswap Total Claims Count for Liquidity Providers",
    "name": "uniswap_total_lp_claims_count",
    "metric": "uniswap_lp_claims",
    "version": "2019-12-22",
    "access": "free",
    "selectors": ["slug"],
    "min_plan": {
      "SANAPI": "pro",
      "SANBASE": "free"
    },
    "aggregation": "last",
    "min_interval": "5m",
    "table": "intraday_metrics",
    "has_incomplete_data": false,
    "data_type": "timeseries",
    "docs_links": ["https://academy.santiment.net/metrics/deprecated-metrics/uniswap-airdrop-metrics"]
  },
  {
    "human_readable_name": "Uniswap Percent Claimed",
    "name": "uniswap_total_claims_percent",
    "metric": "uniswap_percent_claimed",
    "version": "2019-12-22",
    "access": "free",
    "selectors": ["slug"],
    "min_plan": {
      "SANAPI": "pro",
      "SANBASE": "free"
    },
    "aggregation": "last",
    "min_interval": "5m",
    "table": "intraday_metrics",
    "has_incomplete_data": false,
    "data_type": "timeseries",
    "docs_links": ["https://academy.santiment.net/metrics/deprecated-metrics/uniswap-airdrop-metrics"]
  },
  {
    "human_readable_name": "Uniswap Claims Count",
    "name": "uniswap_claims_count",
    "metric": "uniswap_claims_delta",
    "version": "2019-12-22",
    "access": "free",
    "selectors": ["slug"],
    "min_plan": {
      "SANAPI": "pro",
      "SANBASE": "free"
    },
    "aggregation": "sum",
    "min_interval": "5m",
    "table": "intraday_metrics",
    "has_incomplete_data": false,
    "data_type": "timeseries",
    "docs_links": ["https://academy.santiment.net/metrics/deprecated-metrics/uniswap-airdrop-metrics"]
  },
  {
    "human_readable_name": "Uniswap Claims Count for Liquidity Providers",
    "name": "uniswap_lp_claims_count",
    "metric": "uniswap_lp_claims_delta",
    "version": "2019-12-22",
    "access": "free",
    "selectors": ["slug"],
    "min_plan": {
      "SANAPI": "pro",
      "SANBASE": "free"
    },
    "aggregation": "sum",
    "min_interval": "5m",
    "table": "intraday_metrics",
    "has_incomplete_data": false,
    "data_type": "timeseries",
    "docs_links": ["https://academy.santiment.net/metrics/deprecated-metrics/uniswap-airdrop-metrics"]
  },
  {
    "human_readable_name": "Uniswap Claims Count for Users",
    "name": "uniswap_user_claims_count",
    "metric": "uniswap_user_claims_delta",
    "version": "2019-12-22",
    "access": "free",
    "selectors": ["slug"],
    "min_plan": {
      "SANAPI": "pro",
      "SANBASE": "free"
    },
    "aggregation": "sum",
    "min_interval": "5m",
    "table": "intraday_metrics",
    "has_incomplete_data": false,
    "data_type": "timeseries",
    "docs_links": ["https://academy.santiment.net/metrics/deprecated-metrics/uniswap-airdrop-metrics"]
  },
  {
    "human_readable_name": "Uniswap Amount Claimed",
    "name": "uniswap_claims_amount",
    "metric": "uniswap_amount_claimed_delta",
    "version": "2019-12-22",
    "access": "free",
    "selectors": ["slug"],
    "min_plan": {
      "SANAPI": "pro",
      "SANBASE": "free"
    },
    "aggregation": "sum",
    "min_interval": "5m",
    "table": "intraday_metrics",
    "has_incomplete_data": false,
    "data_type": "timeseries",
    "docs_links": ["https://academy.santiment.net/metrics/deprecated-metrics/uniswap-airdrop-metrics"]
  },
  {
    "human_readable_name": "Uniswap Amount Claimed for Liquidity Providers",
    "name": "uniswap_lp_claims_amount",
    "metric": "uniswap_amount_lp_claimed_delta",
    "version": "2019-12-22",
    "access": "free",
    "selectors": ["slug"],
    "min_plan": {
      "SANAPI": "pro",
      "SANBASE": "free"
    },
    "aggregation": "sum",
    "min_interval": "5m",
    "table": "intraday_metrics",
    "has_incomplete_data": false,
    "data_type": "timeseries",
    "docs_links": ["https://academy.santiment.net/metrics/deprecated-metrics/uniswap-airdrop-metrics"]
  },
  {
    "human_readable_name": "Uniswap Amount Claimed for Users",
    "name": "uniswap_user_claims_amount",
    "metric": "uniswap_amount_user_claimed_delta",
    "version": "2019-12-22",
    "access": "free",
    "selectors": ["slug"],
    "min_plan": {
      "SANAPI": "pro",
      "SANBASE": "free"
    },
    "aggregation": "sum",
    "min_interval": "5m",
    "table": "intraday_metrics",
    "has_incomplete_data": false,
    "data_type": "timeseries",
    "docs_links": ["https://academy.santiment.net/metrics/deprecated-metrics/uniswap-airdrop-metrics"]
  }
]
